SingletonProcess/__init__.py
SingletonProcess/examples/basic.py
SingletonProcess/examples/custompids.py
SingletonProcess/examples/poolgroups.py
SingletonProcess/examples/returnval.py
SingletonProcess/examples/verbose.py
singletonprocess-0.1.5.dist-info/licenses/LICENSE
singletonprocess-0.1.5.dist-info/METADATA
singletonprocess-0.1.5.dist-info/WHEEL
singletonprocess-0.1.5.dist-info/top_level.txt
singletonprocess-0.1.5.dist-info/RECORD
