Metadata-Version: 2.4
Name: SingletonProcess
Version: 0.1.5
Summary: Allows existing functions to be run and stopped in seperate processes
Home-page: https://github.com/RobertJN64/SingletonProcess
Author: Robert Nies
Author-email: robertjnies@gmail.com
License: MIT
Classifier: Programming Language :: Python
Classifier: Programming Language :: Python :: 3
Classifier: Programming Language :: Python :: 3 :: Only
Classifier: Programming Language :: Python :: 3.10
Classifier: Programming Language :: Python :: 3.11
Classifier: Programming Language :: Python :: 3.12
Classifier: Programming Language :: Python :: 3.13
Classifier: Programming Language :: Python :: 3.14
Requires-Python: >=3.10
License-File: LICENSE
Requires-Dist: pathos
Dynamic: license-file
